regionmask/__init__.py
regionmask/core/__init__.py
regionmask/core/_deprecate.py
regionmask/core/_geopandas.py
regionmask/core/coords.py
regionmask/core/formatting.py
regionmask/core/mask.py
regionmask/core/options.py
regionmask/core/plot.py
regionmask/core/regions.py
regionmask/core/utils.py
regionmask/defined_regions/__init__.py
regionmask/defined_regions/_ar6.py
regionmask/defined_regions/_natural_earth.py
regionmask/defined_regions/_ressources.py
regionmask/defined_regions/giorgi.py
regionmask/defined_regions/prudence.py
regionmask/defined_regions/srex.py
regionmask/tests/__init__.py
regionmask/tests/test_OneRegion.py
regionmask/tests/test_Regions.py
regionmask/tests/test_create_dataarray.py
regionmask/tests/test_defined_regions.py
regionmask/tests/test_deprecate.py
regionmask/tests/test_formatting.py
regionmask/tests/test_geopandas.py
regionmask/tests/test_mask.py
regionmask/tests/test_mask_3D_frac_approx.py
regionmask/tests/test_mask_cf_xarray.py
regionmask/tests/test_mask_defined_regions.py
regionmask/tests/test_options.py
regionmask/tests/test_plot.py
regionmask/tests/test_segmentize.py
regionmask/tests/test_snap.py
regionmask/tests/test_utils.py
regionmask/tests/test_wrapAngle.py
regionmask/tests/utils.py
regionmask-0.12.1.dist-info/LICENSE
regionmask-0.12.1.dist-info/METADATA
regionmask-0.12.1.dist-info/WHEEL
regionmask-0.12.1.dist-info/top_level.txt
regionmask-0.12.1.dist-info/RECORD
