Metadata-Version: 2.1
Name: regionmask
Version: 0.12.1
Summary: create masks of geospatial regions for arbitrary grids
Home-page: https://github.com/regionmask/regionmask
Author: regionmask Developers
Author-email: mathias.hauser@env.ethz.com
License: MIT
Classifier: Development Status :: 5 - Production/Stable
Classifier: License :: OSI Approved :: MIT License
Classifier: Operating System :: OS Independent
Classifier: Intended Audience :: Science/Research
Classifier: Programming Language :: Python
Classifier: Programming Language :: Python :: 3
Classifier: Programming Language :: Python :: 3.9
Classifier: Programming Language :: Python :: 3.10
Classifier: Programming Language :: Python :: 3.11
Classifier: Programming Language :: Python :: 3.12
Classifier: Topic :: Scientific/Engineering
Classifier: Topic :: Scientific/Engineering :: Atmospheric Science
Classifier: Topic :: Scientific/Engineering :: GIS
Requires-Python: >=3.9
License-File: LICENSE
Requires-Dist: geopandas >=0.10
Requires-Dist: numpy >=1.21
Requires-Dist: packaging >=21.3
Requires-Dist: pooch >=1.4
Requires-Dist: rasterio >=1.2
Requires-Dist: shapely >=1.8
Requires-Dist: xarray >=0.20
Provides-Extra: full
Requires-Dist: cartopy >=0.20 ; extra == 'full'
Requires-Dist: matplotlib >=3.5 ; extra == 'full'
Requires-Dist: cf-xarray >=0.7 ; extra == 'full'
Provides-Extra: plot
Requires-Dist: cartopy >=0.20 ; extra == 'plot'
Requires-Dist: matplotlib >=3.5 ; extra == 'plot'
